<?xml version="1.0" encoding="utf-8"?>
<clothing-items>
 <clothing>
  <id>
   835251014
  </id>
  <name>
   Brooks Pants X-5989
  </name>
  <category>
   Pants
  </category>
  <size>
   XXL
  </size>
  <color>
   Зеленый
  </color>
  <material>
   Полиэстер
  </material>
  <price>
   987442
  </price>
  <rating>
   2.49
  </rating>
  <reviews>
   275425
  </reviews>
  <new>
   +
  </new>
  <exclusive>
   no
  </exclusive>
  <sporty>
   no
  </sporty>
 </clothing>
 <clothing>
  <id>
   694390019
  </id>
  <name>
   New Balance Gloves Y-2861
  </name>
  <category>
   Gloves
  </category>
  <size>
   XL
  </size>
  <color>
   Голубой
  </color>
  <material>
   Нейлон
  </material>
  <price>
   555059
  </price>
  <rating>
   2.39
  </rating>
  <reviews>
   233127
  </reviews>
  <new>
   -
  </new>
  <exclusive>
   yes
  </exclusive>
  <sporty>
   no
  </sporty>
 </clothing>
 <clothing>
  <id>
   134019644
  </id>
  <name>
   Converse Gloves H-2382
  </name>
  <category>
   Gloves
  </category>
  <size>
   L
  </size>
  <color>
   Желтый
  </color>
  <material>
   Кожа
  </material>
  <price>
   592693
  </price>
  <rating>
   3.9
  </rating>
  <reviews>
   601224
  </reviews>
  <new>
   +
  </new>
  <exclusive>
   no
  </exclusive>
 </clothing>
 <clothing>
  <id>
   454106465
  </id>
  <name>
   DC Sweater V-4707
  </name>
  <category>
   Sweater
  </category>
  <size>
   S
  </size>
  <color>
   Желтый
  </color>
  <material>
   Хлопок
  </material>
  <price>
   592462
  </price>
  <rating>
   2.89
  </rating>
  <reviews>
   305275
  </reviews>
  <new>
   -
  </new>
  <exclusive>
   no
  </exclusive>
  <sporty>
   yes
  </sporty>
 </clothing>
 <clothing>
  <id>
   176579444
  </id>
  <name>
   New Balance Shoes P-2289
  </name>
  <category>
   Shoes
  </category>
  <size>
   L
  </size>
  <color>
   Оранжевый
  </color>
  <material>
   Нейлон
  </material>
  <price>
   336761
  </price>
  <rating>
   1.06
  </rating>
  <reviews>
   682188
  </reviews>
  <new>
   -
  </new>
  <exclusive>
   yes
  </exclusive>
  <sporty>
   no
  </sporty>
 </clothing>
 <clothing>
  <id>
   628002711
  </id>
  <name>
   Under Armour Pants A-7121
  </name>
  <category>
   Pants
  </category>
  <size>
   L
  </size>
  <color>
   Желтый
  </color>
  <material>
   Полиэстер
  </material>
  <price>
   978576
  </price>
  <rating>
   2.58
  </rating>
  <reviews>
   910312
  </reviews>
  <new>
   +
  </new>
  <exclusive>
   no
  </exclusive>
  <sporty>
   no
  </sporty>
 </clothing>
 <clothing>
  <id>
   566268243
  </id>
  <name>
   Addidas Sweater L-4441
  </name>
  <category>
   Sweater
  </category>
  <size>
   L
  </size>
  <color>
   Синий
  </color>
  <material>
   Кожа
  </material>
  <price>
   718310
  </price>
  <rating>
   1.86
  </rating>
  <reviews>
   286024
  </reviews>
  <new>
   -
  </new>
  <exclusive>
   no
  </exclusive>
  <sporty>
   yes
  </sporty>
 </clothing>
 <clothing>
  <id>
   195280456
  </id>
  <name>
   Puma Handbags W-8131
  </name>
  <category>
   Handbags
  </category>
  <size>
   L
  </size>
  <color>
   Синий
  </color>
  <material>
   Шелк
  </material>
  <price>
   822870
  </price>
  <rating>
   3.66
  </rating>
  <reviews>
   665016
  </reviews>
  <new>
   -
  </new>
  <exclusive>
   no
  </exclusive>
  <sporty>
   no
  </sporty>
 </clothing>
 <clothing>
  <id>
   914443621
  </id>
  <name>
   Addidas Hat P-3552
  </name>
  <category>
   Hat
  </category>
  <size>
   XXL
  </size>
  <color>
   Голубой
  </color>
  <material>
   Нейлон
  </material>
  <price>
   783287
  </price>
  <rating>
   3.05
  </rating>
  <reviews>
   508060
  </reviews>
  <exclusive>
   no
  </exclusive>
  <sporty>
   yes
  </sporty>
 </clothing>
 <clothing>
  <id>
   163210502
  </id>
  <name>
   Fila Hat U-1139
  </name>
  <category>
   Hat
  </category>
  <size>
   XXL
  </size>
  <color>
   Красный
  </color>
  <material>
   Вискоза
  </material>
  <price>
   143286
  </price>
  <rating>
   1.61
  </rating>
  <reviews>
   309806
  </reviews>
  <exclusive>
   no
  </exclusive>
  <sporty>
   yes
  </sporty>
 </clothing>
 <clothing>
  <id>
   207534272
  </id>
  <name>
   Vans Socks R-7432
  </name>
  <category>
   Socks
  </category>
  <size>
   L
  </size>
  <color>
   Красный
  </color>
  <material>
   Кожа
  </material>
  <price>
   928987
  </price>
  <rating>
   4.6
  </rating>
  <reviews>
   245182
  </reviews>
  <new>
   +
  </new>
  <exclusive>
   no
  </exclusive>
 </clothing>
 <clothing>
  <id>
   231130506
  </id>
  <name>
   DC Handbags P-3815
  </name>
  <category>
   Handbags
  </category>
  <size>
   L
  </size>
  <color>
   Оранжевый
  </color>
  <material>
   Вискоза
  </material>
  <price>
   797242
  </price>
  <rating>
   2.98
  </rating>
  <reviews>
   88662
  </reviews>
  <sporty>
   no
  </sporty>
 </clothing>
 <clothing>
  <id>
   988271888
  </id>
  <name>
   Nike Jeans G-4658
  </name>
  <category>
   Jeans
  </category>
  <size>
   XXL
  </size>
  <color>
   Синий
  </color>
  <material>
   Лен
  </material>
  <price>
   145812
  </price>
  <rating>
   4.66
  </rating>
  <reviews>
   699216
  </reviews>
  <sporty>
   no
  </sporty>
 </clothing>
 <clothing>
  <id>
   938821494
  </id>
  <name>
   Vans Shirt J-3449
  </name>
  <category>
   Shirt
  </category>
  <size>
   L
  </size>
  <color>
   Голубой
  </color>
  <material>
   Лен
  </material>
  <price>
   172639
  </price>
  <rating>
   4.73
  </rating>
  <reviews>
   937125
  </reviews>
  <new>
   -
  </new>
 </clothing>
 <clothing>
  <id>
   648982468
  </id>
  <name>
   Vans Shoes Z-3967
  </name>
  <category>
   Shoes
  </category>
  <size>
   XXL
  </size>
  <color>
   Желтый
  </color>
  <material>
   Полиэстер
  </material>
  <price>
   324278
  </price>
  <rating>
   2.32
  </rating>
  <reviews>
   632303
  </reviews>
  <new>
   -
  </new>
  <exclusive>
   no
  </exclusive>
 </clothing>
 <clothing>
  <id>
   477719636
  </id>
  <name>
   Ellesse Gloves H-2861
  </name>
  <category>
   Gloves
  </category>
  <size>
   M
  </size>
  <color>
   Оранжевый
  </color>
  <material>
   Хлопок
  </material>
  <price>
   688381
  </price>
  <rating>
   2.78
  </rating>
  <reviews>
   999055
  </reviews>
  <new>
   -
  </new>
  <exclusive>
   no
  </exclusive>
 </clothing>
 <clothing>
  <id>
   390877871
  </id>
  <name>
   Under Armour Shoes Z-7706
  </name>
  <category>
   Shoes
  </category>
  <size>
   XL
  </size>
  <color>
   Голубой
  </color>
  <material>
   Хлопок
  </material>
  <price>
   681684
  </price>
  <rating>
   1.4
  </rating>
  <reviews>
   33169
  </reviews>
  <new>
   +
  </new>
 </clothing>
 <clothing>
  <id>
   986884203
  </id>
  <name>
   Vans Handbags W-6812
  </name>
  <category>
   Handbags
  </category>
  <size>
   L
  </size>
  <color>
   Голубой
  </color>
  <material>
   Нейлон
  </material>
  <price>
   706671
  </price>
  <rating>
   1.34
  </rating>
  <reviews>
   651334
  </reviews>
  <exclusive>
   no
  </exclusive>
  <sporty>
   no
  </sporty>
 </clothing>
 <clothing>
  <id>
   208871079
  </id>
  <name>
   New Balance Gloves N-2691
  </name>
  <category>
   Gloves
  </category>
  <size>
   XL
  </size>
  <color>
   Оранжевый
  </color>
  <material>
   Лен
  </material>
  <price>
   933628
  </price>
  <rating>
   3.84
  </rating>
  <reviews>
   338977
  </reviews>
  <new>
   +
  </new>
  <exclusive>
   yes
  </exclusive>
  <sporty>
   no
  </sporty>
 </clothing>
 <clothing>
  <id>
   542493195
  </id>
  <name>
   PleinSport Jeans L-5457
  </name>
  <category>
   Jeans
  </category>
  <size>
   L
  </size>
  <color>
   Фиолетовый
  </color>
  <material>
   Лен
  </material>
  <price>
   897208
  </price>
  <rating>
   3.43
  </rating>
  <reviews>
   60555
  </reviews>
  <new>
   -
  </new>
  <sporty>
   yes
  </sporty>
 </clothing>
 <clothing>
  <id>
   501260455
  </id>
  <name>
   PleinSport Jacket R-3350
  </name>
  <category>
   Jacket
  </category>
  <size>
   S
  </size>
  <color>
   Синий
  </color>
  <material>
   Вискоза
  </material>
  <price>
   717559
  </price>
  <rating>
   1.31
  </rating>
  <reviews>
   960159
  </reviews>
  <new>
   -
  </new>
  <exclusive>
   yes
  </exclusive>
 </clothing>
 <clothing>
  <id>
   621310666
  </id>
  <name>
   Reebok Belts E-8592
  </name>
  <category>
   Belts
  </category>
  <size>
   XXL
  </size>
  <color>
   Зеленый
  </color>
  <material>
   Хлопок
  </material>
  <price>
   426187
  </price>
  <rating>
   1.3
  </rating>
  <reviews>
   501299
  </reviews>
  <new>
   -
  </new>
  <exclusive>
   no
  </exclusive>
 </clothing>
 <clothing>
  <id>
   432831647
  </id>
  <name>
   PleinSport Gloves I-9311
  </name>
  <category>
   Gloves
  </category>
  <size>
   S
  </size>
  <color>
   Голубой
  </color>
  <material>
   Кожа
  </material>
  <price>
   311312
  </price>
  <rating>
   1.6
  </rating>
  <reviews>
   803248
  </reviews>
  <sporty>
   yes
  </sporty>
 </clothing>
 <clothing>
  <id>
   667536472
  </id>
  <name>
   Lacoste Dress N-2329
  </name>
  <category>
   Dress
  </category>
  <size>
   M
  </size>
  <color>
   Синий
  </color>
  <material>
   Вискоза
  </material>
  <price>
   192269
  </price>
  <rating>
   1.1
  </rating>
  <reviews>
   200128
  </reviews>
  <exclusive>
   no
  </exclusive>
  <sporty>
   no
  </sporty>
 </clothing>
 <clothing>
  <id>
   955675694
  </id>
  <name>
   PleinSport Gloves Q-4038
  </name>
  <category>
   Gloves
  </category>
  <size>
   XXL
  </size>
  <color>
   Зеленый
  </color>
  <material>
   Лен
  </material>
  <price>
   249755
  </price>
  <rating>
   2.97
  </rating>
  <reviews>
   584490
  </reviews>
  <exclusive>
   no
  </exclusive>
  <sporty>
   no
  </sporty>
 </clothing>
 <clothing>
  <id>
   614910244
  </id>
  <name>
   Adidas Skirt U-6721
  </name>
  <category>
   Skirt
  </category>
  <size>
   M
  </size>
  <color>
   Фиолетовый
  </color>
  <material>
   Лен
  </material>
  <price>
   442356
  </price>
  <rating>
   1.88
  </rating>
  <reviews>
   984537
  </reviews>
  <new>
   +
  </new>
  <exclusive>
   no
  </exclusive>
  <sporty>
   no
  </sporty>
 </clothing>
 <clothing>
  <id>
   512952494
  </id>
  <name>
   PleinSport Socks W-1187
  </name>
  <category>
   Socks
  </category>
  <size>
   L
  </size>
  <color>
   Зеленый
  </color>
  <material>
   Нейлон
  </material>
  <price>
   819034
  </price>
  <rating>
   2.98
  </rating>
  <reviews>
   744191
  </reviews>
  <new>
   -
  </new>
  <exclusive>
   no
  </exclusive>
  <sporty>
   yes
  </sporty>
 </clothing>
 <clothing>
  <id>
   632481983
  </id>
  <name>
   PleinSport Jacket C-6083
  </name>
  <category>
   Jacket
  </category>
  <size>
   XXL
  </size>
  <color>
   Фиолетовый
  </color>
  <material>
   Шелк
  </material>
  <price>
   708436
  </price>
  <rating>
   4.59
  </rating>
  <reviews>
   536760
  </reviews>
  <exclusive>
   yes
  </exclusive>
  <sporty>
   yes
  </sporty>
 </clothing>
 <clothing>
  <id>
   748799290
  </id>
  <name>
   Puma Gloves N-2627
  </name>
  <category>
   Gloves
  </category>
  <size>
   S
  </size>
  <color>
   Оранжевый
  </color>
  <material>
   Нейлон
  </material>
  <price>
   491483
  </price>
  <rating>
   2.48
  </rating>
  <reviews>
   251279
  </reviews>
  <exclusive>
   no
  </exclusive>
  <sporty>
   yes
  </sporty>
 </clothing>
 <clothing>
  <id>
   244997496
  </id>
  <name>
   Fila Jeans X-6049
  </name>
  <category>
   Jeans
  </category>
  <size>
   XXL
  </size>
  <color>
   Желтый
  </color>
  <material>
   Нейлон
  </material>
  <price>
   512778
  </price>
  <rating>
   4.5
  </rating>
  <reviews>
   4144
  </reviews>
  <exclusive>
   no
  </exclusive>
  <sporty>
   yes
  </sporty>
 </clothing>
</clothing-items>
