<?xml version="1.0" encoding="utf-8"?>
<clothing-items>
 <clothing>
  <id>
   179919816
  </id>
  <name>
   Puma T-shirt H-1904
  </name>
  <category>
   T-shirt
  </category>
  <size>
   XXL
  </size>
  <color>
   Красный
  </color>
  <material>
   Шелк
  </material>
  <price>
   290791
  </price>
  <rating>
   2.44
  </rating>
  <reviews>
   551572
  </reviews>
  <new>
   -
  </new>
 </clothing>
 <clothing>
  <id>
   127832295
  </id>
  <name>
   PleinSport Shoes L-1832
  </name>
  <category>
   Shoes
  </category>
  <size>
   L
  </size>
  <color>
   Оранжевый
  </color>
  <material>
   Шерсть
  </material>
  <price>
   853398
  </price>
  <rating>
   3.3
  </rating>
  <reviews>
   143298
  </reviews>
 </clothing>
 <clothing>
  <id>
   148494271
  </id>
  <name>
   New Balance Gloves I-8246
  </name>
  <category>
   Gloves
  </category>
  <size>
   L
  </size>
  <color>
   Красный
  </color>
  <material>
   Шелк
  </material>
  <price>
   190214
  </price>
  <rating>
   4.83
  </rating>
  <reviews>
   516645
  </reviews>
  <sporty>
   no
  </sporty>
 </clothing>
 <clothing>
  <id>
   651519815
  </id>
  <name>
   Addidas Blouse G-9083
  </name>
  <category>
   Blouse
  </category>
  <size>
   L
  </size>
  <color>
   Красный
  </color>
  <material>
   Нейлон
  </material>
  <price>
   360261
  </price>
  <rating>
   4.95
  </rating>
  <reviews>
   202338
  </reviews>
  <new>
   -
  </new>
  <sporty>
   yes
  </sporty>
 </clothing>
 <clothing>
  <id>
   617812494
  </id>
  <name>
   Reebok Sweater I-9661
  </name>
  <category>
   Sweater
  </category>
  <size>
   S
  </size>
  <color>
   Синий
  </color>
  <material>
   Шерсть
  </material>
  <price>
   710957
  </price>
  <rating>
   2.16
  </rating>
  <reviews>
   24005
  </reviews>
  <new>
   +
  </new>
 </clothing>
 <clothing>
  <id>
   726734634
  </id>
  <name>
   Puma Dress E-7102
  </name>
  <category>
   Dress
  </category>
  <size>
   L
  </size>
  <color>
   Голубой
  </color>
  <material>
   Кожа
  </material>
  <price>
   312134
  </price>
  <rating>
   4.42
  </rating>
  <reviews>
   335783
  </reviews>
  <exclusive>
   yes
  </exclusive>
  <sporty>
   no
  </sporty>
 </clothing>
 <clothing>
  <id>
   532342919
  </id>
  <name>
   Puma Shoes K-6945
  </name>
  <category>
   Shoes
  </category>
  <size>
   S
  </size>
  <color>
   Синий
  </color>
  <material>
   Вискоза
  </material>
  <price>
   908584
  </price>
  <rating>
   3.04
  </rating>
  <reviews>
   112057
  </reviews>
  <new>
   +
  </new>
  <sporty>
   yes
  </sporty>
 </clothing>
 <clothing>
  <id>
   855194954
  </id>
  <name>
   Ellesse Hat N-9423
  </name>
  <category>
   Hat
  </category>
  <size>
   XL
  </size>
  <color>
   Зеленый
  </color>
  <material>
   Нейлон
  </material>
  <price>
   449259
  </price>
  <rating>
   3.16
  </rating>
  <reviews>
   992645
  </reviews>
  <new>
   +
  </new>
  <exclusive>
   no
  </exclusive>
 </clothing>
 <clothing>
  <id>
   832306111
  </id>
  <name>
   Puma Sweater M-6315
  </name>
  <category>
   Sweater
  </category>
  <size>
   XL
  </size>
  <color>
   Оранжевый
  </color>
  <material>
   Кожа
  </material>
  <price>
   822255
  </price>
  <rating>
   1.62
  </rating>
  <reviews>
   744739
  </reviews>
  <new>
   -
  </new>
  <sporty>
   no
  </sporty>
 </clothing>
 <clothing>
  <id>
   702540702
  </id>
  <name>
   Asics Shoes F-7721
  </name>
  <category>
   Shoes
  </category>
  <size>
   XXL
  </size>
  <color>
   Красный
  </color>
  <material>
   Шерсть
  </material>
  <price>
   757920
  </price>
  <rating>
   2.2
  </rating>
  <reviews>
   453954
  </reviews>
  <new>
   +
  </new>
  <exclusive>
   no
  </exclusive>
  <sporty>
   no
  </sporty>
 </clothing>
 <clothing>
  <id>
   694470362
  </id>
  <name>
   Nike Blouse R-3043
  </name>
  <category>
   Blouse
  </category>
  <size>
   S
  </size>
  <color>
   Фиолетовый
  </color>
  <material>
   Хлопок
  </material>
  <price>
   642892
  </price>
  <rating>
   1.69
  </rating>
  <reviews>
   708581
  </reviews>
  <new>
   -
  </new>
  <exclusive>
   yes
  </exclusive>
  <sporty>
   no
  </sporty>
 </clothing>
 <clothing>
  <id>
   846517818
  </id>
  <name>
   DC Dress X-8816
  </name>
  <category>
   Dress
  </category>
  <size>
   S
  </size>
  <color>
   Оранжевый
  </color>
  <material>
   Кожа
  </material>
  <price>
   635998
  </price>
  <rating>
   3.01
  </rating>
  <reviews>
   88938
  </reviews>
  <exclusive>
   no
  </exclusive>
 </clothing>
 <clothing>
  <id>
   136990127
  </id>
  <name>
   Nike Dress X-8142
  </name>
  <category>
   Dress
  </category>
  <size>
   S
  </size>
  <color>
   Красный
  </color>
  <material>
   Нейлон
  </material>
  <price>
   998572
  </price>
  <rating>
   3.43
  </rating>
  <reviews>
   417271
  </reviews>
  <new>
   -
  </new>
  <exclusive>
   yes
  </exclusive>
 </clothing>
 <clothing>
  <id>
   849211308
  </id>
  <name>
   Adidas Umbrellas I-3498
  </name>
  <category>
   Umbrellas
  </category>
  <size>
   L
  </size>
  <color>
   Зеленый
  </color>
  <material>
   Полиэстер
  </material>
  <price>
   536957
  </price>
  <rating>
   1.3
  </rating>
  <reviews>
   448530
  </reviews>
  <new>
   -
  </new>
  <sporty>
   no
  </sporty>
 </clothing>
 <clothing>
  <id>
   545894067
  </id>
  <name>
   Ellesse Skirt L-3805
  </name>
  <category>
   Skirt
  </category>
  <size>
   S
  </size>
  <color>
   Фиолетовый
  </color>
  <material>
   Нейлон
  </material>
  <price>
   936747
  </price>
  <rating>
   1.09
  </rating>
  <reviews>
   906164
  </reviews>
  <new>
   -
  </new>
  <sporty>
   no
  </sporty>
 </clothing>
 <clothing>
  <id>
   170558681
  </id>
  <name>
   Converse Sweater F-3433
  </name>
  <category>
   Sweater
  </category>
  <size>
   XXL
  </size>
  <color>
   Зеленый
  </color>
  <material>
   Вискоза
  </material>
  <price>
   474337
  </price>
  <rating>
   4.31
  </rating>
  <reviews>
   87834
  </reviews>
  <exclusive>
   no
  </exclusive>
 </clothing>
 <clothing>
  <id>
   950243383
  </id>
  <name>
   Vans Jacket D-1272
  </name>
  <category>
   Jacket
  </category>
  <size>
   M
  </size>
  <color>
   Желтый
  </color>
  <material>
   Вискоза
  </material>
  <price>
   409845
  </price>
  <rating>
   1.37
  </rating>
  <reviews>
   978406
  </reviews>
  <new>
   +
  </new>
  <sporty>
   yes
  </sporty>
 </clothing>
 <clothing>
  <id>
   672366241
  </id>
  <name>
   Nike Sweater M-6269
  </name>
  <category>
   Sweater
  </category>
  <size>
   XXL
  </size>
  <color>
   Оранжевый
  </color>
  <material>
   Нейлон
  </material>
  <price>
   676935
  </price>
  <rating>
   1.57
  </rating>
  <reviews>
   147470
  </reviews>
  <exclusive>
   yes
  </exclusive>
 </clothing>
 <clothing>
  <id>
   225791039
  </id>
  <name>
   Asics Skirt N-3214
  </name>
  <category>
   Skirt
  </category>
  <size>
   XL
  </size>
  <color>
   Фиолетовый
  </color>
  <material>
   Шерсть
  </material>
  <price>
   332539
  </price>
  <rating>
   2.16
  </rating>
  <reviews>
   25945
  </reviews>
  <new>
   +
  </new>
  <exclusive>
   no
  </exclusive>
  <sporty>
   no
  </sporty>
 </clothing>
</clothing-items>
